coolmathcd/__init__.py
coolmathcd/math_operations.py
coolmathcd-0.0.4.dist-info/METADATA
coolmathcd-0.0.4.dist-info/WHEEL
coolmathcd-0.0.4.dist-info/top_level.txt
coolmathcd-0.0.4.dist-info/RECORD
