Metadata-Version: 2.1
Name: coolmathcd
Version: 0.0.4
Summary: A simple math library
Home-page: https://gitlab.com/theant72/coolmathcd.git
Author: Antonello Mangone
Author-email: antonello.mangone@gmail.com
Classifier: Development Status :: 3 - Alpha
Classifier: Intended Audience :: Developers
Classifier: License :: OSI Approved :: MIT License
Classifier: Programming Language :: Python :: 3.12
